mcp_justwatch/__init__.py
mcp_justwatch/server.py
mcp_justwatch-0.0.1.dist-info/METADATA
mcp_justwatch-0.0.1.dist-info/WHEEL
mcp_justwatch-0.0.1.dist-info/entry_points.txt
mcp_justwatch-0.0.1.dist-info/RECORD
