Metadata-Version: 2.4
Name: mcp-justwatch
Version: 0.0.1
Summary: MCP server for JustWatch streaming availability data.
Author-email: Karol Krizka <kkrizka@gmail.com>
Requires-Python: >=3.11
Requires-Dist: fastmcp
Requires-Dist: simple-justwatch-python-api
Provides-Extra: dev
Requires-Dist: black>=23.0.0; extra == 'dev'
Requires-Dist: pytest-asyncio>=0.21.0; extra == 'dev'
Requires-Dist: pytest>=7.0.0; extra == 'dev'
Requires-Dist: ruff>=0.1.0; extra == 'dev'
